{"nodes": [{"id": "data_projects_design_system_ci_changelog_md", "label": "CHANGELOG.md", "file_type": "document", "source_file": "CHANGELOG.md", "source_location": "L1"}, {"id": "design_system_ci_changelog_changelog", "label": "Changelog", "file_type": "document", "source_file": "CHANGELOG.md", "source_location": "L1"}, {"id": "design_system_ci_changelog_0_1_0_2026_06_16", "label": "[0.1.0] - 2026-06-16", "file_type": "document", "source_file": "CHANGELOG.md", "source_location": "L5"}, {"id": "design_system_ci_changelog_added", "label": "Added", "file_type": "document", "source_file": "CHANGELOG.md", "source_location": "L7"}], "edges": [{"source": "data_projects_design_system_ci_changelog_md", "target": "design_system_ci_changelog_changelog", "relation": "contains", "confidence": "EXTRACTED", "source_file": "CHANGELOG.md", "source_location": "L1", "weight": 1.0}, {"source": "design_system_ci_changelog_changelog", "target": "design_system_ci_changelog_0_1_0_2026_06_16", "relation": "contains", "confidence": "EXTRACTED", "source_file": "CHANGELOG.md", "source_location": "L5", "weight": 1.0}, {"source": "design_system_ci_changelog_0_1_0_2026_06_16", "target": "design_system_ci_changelog_added", "relation": "contains", "confidence": "EXTRACTED", "source_file": "CHANGELOG.md", "source_location": "L7", "weight": 1.0}], "input_tokens": 0, "output_tokens": 0}