{"nodes": [{"id": "data_projects_design_system_ci_package_json", "label": "package.json", "file_type": "code", "source_file": "package.json", "source_location": "L1"}, {"id": "design_system_ci_package_name", "label": "name", "file_type": "code", "source_file": "package.json", "source_location": "L2"}, {"id": "design_system_ci_package_private", "label": "private", "file_type": "code", "source_file": "package.json", "source_location": "L3"}, {"id": "design_system_ci_package_workspaces", "label": "workspaces", "file_type": "code", "source_file": "package.json", "source_location": "L4"}, {"id": "design_system_ci_package_scripts", "label": "scripts", "file_type": "code", "source_file": "package.json", "source_location": "L7"}, {"id": "design_system_ci_package_scripts_build", "label": "build", "file_type": "code", "source_file": "package.json", "source_location": "L8"}, {"id": "design_system_ci_package_scripts_test", "label": "test", "file_type": "code", "source_file": "package.json", "source_location": "L9"}, {"id": "design_system_ci_package_scripts_dev", "label": "dev", "file_type": "code", "source_file": "package.json", "source_location": "L10"}, {"id": "design_system_ci_package_devdependencies", "label": "devDependencies", "file_type": "code", "source_file": "package.json", "source_location": "L12"}, {"id": "design_system_ci_package_devdependencies_vitest_coverage_v8", "label": "@vitest/coverage-v8", "file_type": "code", "source_file": "package.json", "source_location": "L13"}], "edges": [{"source": "data_projects_design_system_ci_package_json", "target": "design_system_ci_package_name", "relation": "contains", "confidence": "EXTRACTED", "source_file": "package.json", "source_location": "L2", "weight": 1.0}, {"source": "data_projects_design_system_ci_package_json", "target": "design_system_ci_package_private", "relation": "contains", "confidence": "EXTRACTED", "source_file": "package.json", "source_location": "L3", "weight": 1.0}, {"source": "data_projects_design_system_ci_package_json", "target": "design_system_ci_package_workspaces", "relation": "contains", "confidence": "EXTRACTED", "source_file": "package.json", "source_location": "L4", "weight": 1.0}, {"source": "design_system_ci_package_workspaces", "target": "ref_packages", "relation": "extends", "confidence": "EXTRACTED", "source_file": "package.json", "source_location": "L4", "weight": 1.0, "context": "import"}, {"source": "data_projects_design_system_ci_package_json", "target": "design_system_ci_package_scripts", "relation": "contains", "confidence": "EXTRACTED", "source_file": "package.json", "source_location": "L7", "weight": 1.0}, {"source": "design_system_ci_package_scripts", "target": "design_system_ci_package_scripts_build", "relation": "contains", "confidence": "EXTRACTED", "source_file": "package.json", "source_location": "L8", "weight": 1.0}, {"source": "design_system_ci_package_scripts", "target": "design_system_ci_package_scripts_test", "relation": "contains", "confidence": "EXTRACTED", "source_file": "package.json", "source_location": "L9", "weight": 1.0}, {"source": "design_system_ci_package_scripts", "target": "design_system_ci_package_scripts_dev", "relation": "contains", "confidence": "EXTRACTED", "source_file": "package.json", "source_location": "L10", "weight": 1.0}, {"source": "data_projects_design_system_ci_package_json", "target": "design_system_ci_package_devdependencies", "relation": "contains", "confidence": "EXTRACTED", "source_file": "package.json", "source_location": "L12", "weight": 1.0}, {"source": "design_system_ci_package_devdependencies", "target": "design_system_ci_package_devdependencies_vitest_coverage_v8", "relation": "contains", "confidence": "EXTRACTED", "source_file": "package.json", "source_location": "L13", "weight": 1.0}, {"source": "design_system_ci_package_devdependencies_vitest_coverage_v8", "target": "vitest_coverage_v8", "relation": "imports", "confidence": "EXTRACTED", "source_file": "package.json", "source_location": "L13", "weight": 1.0, "context": "import"}]}